<?xml version="1.0" encoding="utf-8" ?>
<dwsync>
<file name="_common.php" server="auddbs7898.cafe24.com" local="131932028479631381" remote="131804287200000000" Dst="0" />
<file name="group.php" server="auddbs7898.cafe24.com" local="131932028496062321" remote="131804284200000000" Dst="0" />
<file name="head.php" server="auddbs7898.cafe24.com" local="131932028496152326" remote="131804284200000000" Dst="0" />
<file name="head.sub.php" server="auddbs7898.cafe24.com" local="131932028496152326" remote="131804284200000000" Dst="0" />
<file name="index.php" server="auddbs7898.cafe24.com" local="131932028532534407" remote="131804284800000000" Dst="0" />
<file name="readme.txt" server="auddbs7898.cafe24.com" local="131932029454907164" remote="131804286000000000" Dst="0" />
<file name="screenshot.png" server="auddbs7898.cafe24.com" local="131932029455027170" remote="131804286000000000" Dst="0" />
<file name="tail.sub.php" server="auddbs7898.cafe24.com" local="131932030240882119" remote="131804287200000000" Dst="0" />
<file name="tail.php" server="auddbs7898.cafe24.com" local="131932030240932122" remote="131804287200000000" Dst="0" />
<file name="theme.config.php" server="auddbs7898.cafe24.com" local="131932030241032127" remote="131804287200000000" Dst="0" />
</dwsync>