<xml version='1.0' encoding="utf-8">
		<info>
		<brand>
					<폴더>ReVintage_</폴더>
					<대표이미지번호>6</대표이미지번호>
		<순번>34</순번>
		<날짜>2018.08.10</날짜>
		<호실>414호</호실>
		<브랜드명>르빈티지</브랜드명>
		<로고경로></로고경로>
		<영문명>Re:Vintage</영문명>
		<성함>황혜영</성함>
		<data6>
		</data6>
		<연락처>010-8923-3297</연락처>
		<이메일>revintage@naver.com</이메일>
		<사이트주소>http://　</사이트주소>
		<SNS>instagram.com/revintage2016</SNS>
		<소재>가죽</소재>
		<분류>잡화</분류>
		<현황품목수>3</현황품목수>
		<업체소개>오랫동안 인류의 실생활에 사용되어진 가죽을 현재 시점에 맞추어 한국적인 감성과 이미지, 전통 문양 등 고전적인 요소를 현대적인 디자인과 IT기술로 작업하는 가죽브랜드입니다.
		새로운 공예재료로 재해석한 빈티지하고 레트로한 가죽제품을 만나보세요.</업체소개>
		
	   </brand>
	   <작품들>
	   <work>
	   <data0>86</data0>
	  <data1>가죽</data1>
	  <data2>잡화</data2>
	  <data3>　</data3>
	  <data4>　</data4>
	  <data5>삼색 양귀비 미니 지갑</data5>
	  <data6>르빈티지</data6>
	  <data7>106 x 76 x 10</data7>
	  <data8>삼색 배색</data8>
	  <data9>천연 소가죽</data9>
	  <data10>　</data10>
	  <data11>₩28,000</data11>
	  <data12>천연소가죽 3가지 컬러를    배색하여 레이져컷팅으로 양귀비 형상을 내어만든 미니지갑. / 
      카드와 명함 및 지폐 등을 수납 가능하여 다용도로 사용가능합니다.</data12>
	  <data13>불이나 물에 취약합니다.</data13>
	  <data14>　</data14>
	  </work>
	  <work><data0>87</data0>
	  <data1>가죽</data1>
	  <data2>잡화</data2>
	  <data3>　</data3>
	  <data4>　</data4>
	  <data5>아이스마일유 교통카드 케이스</data5>
	  <data6>르빈티지</data6>
	  <data7>75 x 110 x 10</data7>
	  <data8>7    colors, 투톤 배색</data8>
	  <data9>천연    소가죽</data9>
	  <data10>　</data10>
	  <data11>₩42,000</data11>
	  <data12>천연    소가죽 7가지 칼라를 사용하여 만든 교통카드 케이스로 안쪽에 총 4장의 카드를 꽂을수 있다. / 
      레이저컷팅으로 가공한 가죽을 서울시 지도 모양의 투 톤으로 형상화하고, 웃는 모습으로 의인화한 한강과 슬로건인 아이스마일유(I.    Smile. U)를 무광금색 불박으로 표현하였다. 목에 거는 스트랩은 한국 전통 분위기를 낼 수 있도록 매듭지어 그 자체가 장식이 될 수    있다.</data12>
	  <data13>불이나    물에 취약합니다.</data13>
	  <data14>　</data14>
	  </work>
	  
	  <work><data0>88</data0>
	  <data1>가죽</data1>
	  <data2>잡화</data2>
	  <data3>　</data3>
	  <data4>　</data4>
	  <data5>아이스마일유 여권 케이스</data5>
	  <data6>르빈티지</data6>
	  <data7>100 x 145 x 10</data7>
	  <data8>　</data8>
	  <data9>천연    소가죽</data9>
	  <data10>　</data10>
	  <data11>₩48,000</data11>
	  <data12>천연    소가죽 7가지 칼라를 사용하여 만든 여권 케이스로 안쪽에도 카드 및 티켓 등을 넣을수 있고 여권도 편하게 쓸수 있도록 하였다. / 
      옛 것과 최첨단의 이미지를 고루 가지고 있는 서울시의 특징대로 오래된 공예재료인 가죽을 레이저컷팅으로 가공하여 서울시의 지도 모양을 투    톤으로 형상화 하였다. / 
      서울의 중심인 한강을 사람의 웃는 모습으로 연상하여 붓자국으로 표현한 서울의 물길과 이를 슬로건화 한 아이스마일유(I. Smile.    U)를 무광금색 불박으로 표현하였다.</data12>
	  <data13>불이나    물에 취약합니다.</data13>
	  <data14>　</data14>
	  </work>
	  <work><data0>89</data0>
	  <data1>가죽</data1>
	  <data2>잡화</data2>
	  <data3>　</data3>
	  <data4>　</data4>
	  <data5> 궁 미니지갑 </data5>
	  <data6>르빈티지</data6>
	  <data7>106 x 76 x 10</data7>
	  <data8>　</data8>
	  <data9>천연 소가죽</data9>
	  <data10>　</data10>
	  <data11>₩28,000</data11>
	  <data12>푸른 하늘을 배경으로 보이는    궁의 형상을 천연소가죽 3가지 컬러를 배색하고레이져컷팅으로 표현하여 디자인하고 제작한 미니지갑. / 
      카드와 명함 및 지폐 등 수납 가능하여 다용도로 사용가능합니다.</data12>
	  <data13>불이나 물에 취약합니다.</data13>
	  <data14>　</data14>
	  </work>
	  <work><data0>90</data0>
	  <data1>가죽</data1>
	  <data2>잡화</data2>
	  <data3>　</data3>
	  <data4>　</data4>
	  <data5>플라워 장지갑</data5>
	  <data6>르빈티지</data6>
	  <data7>195 x 105 x 10</data7>
	  <data8>　</data8>
	  <data9>천연 소가죽</data9>
	  <data10>　</data10>
	  <data11>₩88,000</data11>
	  <data12>워터페인팅 느낌의 플라워    패턴을 천연가죽에 프린트하여 제작된 장지갑으로 내부에 카드칸과 지폐칸, 지퍼칸으로 구분되어 있으며, 스마트폰도 넣을 수 있는 넉넉한    사이즈로 외출시 하나만 들고 나갈수 있도록 간편하면서도 편리하게 디자인하였다.</data12>
	  <data13>불이나 물에 취약합니다.</data13>
	  <data14>　</data14>
	  </work>
	  
	  <work><data0>91</data0>
	  <data1>가죽</data1>
	  <data2>잡화</data2>
	  <data3>　</data3>
	  <data4>　</data4>
	  <data5>남대문 여권 케이스</data5>
	  <data6>르빈티지</data6>
	  <data7>95 x 140 x 10</data7>
	  <data8>　</data8>
	  <data9>천연 소가죽</data9>
	  <data10>　</data10>
	  <data11>₩48,000</data11>
	  <data12>천연소가죽으로 만든    여권케이스로, 남대문 형상을 투톤 컬러로, 금박으로는 I love KOREA를 넣어 한국적 이미지를 극대화하였다.</data12>
	  <data13>불이나 물에 취약합니다.</data13>
	  <data14>　</data14>
	  </work></작품들>
		</info>
		</xml>  

